CHANGES
LICENSE
MANIFEST.in
README.md
setup.py
bin/guilocker
guilocker/__init__.py
guilocker.egg-info/PKG-INFO
guilocker.egg-info/SOURCES.txt
guilocker.egg-info/dependency_links.txt
guilocker.egg-info/top_level.txt
guilocker/Core/GuiLocker.py
guilocker/Core/Module.py
guilocker/Core/__init__.py
guilocker/Daemon/Guilockerd.py
guilocker/Daemon/Module.py
guilocker/Daemon/__init__.py