Metadata-Version: 1.1
Name: guilocker
Version: 0.2.1
Summary: UNKNOWN
Home-page: https://github.com/riemannulus/GuiLocker
Author: Lee, Suho
Author-email: riemannulus@hitagi.moe
License: MIT
Keywords: GuiLocker BitLocker
Platform: UNKNOWN
Classifier: Programming Language :: Python :: 3.7
Classifier: License :: OSI Approved :: MIT License
